watcher_fs/__init__.py
watcher_fs/async_watcher.py
watcher_fs/cli.py
watcher_fs/watcher.py
watcher_fs/actions/__init__.py
watcher_fs/actions/cmd.py
watcher_fs/actions/notify.py
watcher_fs-1.4.dist-info/licenses/LICENSE
watcher_fs-1.4.dist-info/METADATA
watcher_fs-1.4.dist-info/WHEEL
watcher_fs-1.4.dist-info/entry_points.txt
watcher_fs-1.4.dist-info/top_level.txt
watcher_fs-1.4.dist-info/RECORD
