Metadata-Version: 2.4
Name: watcher-fs
Version: 1.4
Summary: A Python package for monitoring file system changes
Author-email: Pavel Křupala <pavel.krupala@gmail.com>
License-Expression: MIT
Project-URL: Homepage, https://github.com/pavelkrupala/watcher-fs
Project-URL: Documentation, https://pavelkrupala.github.io/watcher-fs
Classifier: Programming Language :: Python :: 3.11
Classifier: Programming Language :: Python :: 3.12
Classifier: Programming Language :: Python :: 3.13
Classifier: Operating System :: OS Independent
Requires-Python: >=3.11
License-File: LICENSE
Requires-Dist: click>=8.1.0
Dynamic: license-file
